Metadata-Version: 1.2
Name: safexzutils
Version: 0.1.3
Summary: independent functions
Home-page: UNKNOWN
Author: safeutils
Author-email: back_man007@163.com
License: LICENSE.txt
Platform: UNKNOWN
Requires-Python: >=3
